sql_configr/__init__.py
sql_configr/sql_configr.py
sql_configr-0.0.2.dist-info/LICENSE.txt
sql_configr-0.0.2.dist-info/METADATA
sql_configr-0.0.2.dist-info/WHEEL
sql_configr-0.0.2.dist-info/top_level.txt
sql_configr-0.0.2.dist-info/RECORD
