Metadata-Version: 2.1
Name: sql-configr
Version: 0.0.2
Summary: Quickly create a MySQL credentials json file
Home-page: https://github.com/rrickgauer/sql_configr
Author: Ryan Rickgauer
Author-email: rrickgauer1@gmail.com
License: UNKNOWN
Platform: UNKNOWN
Classifier: Programming Language :: Python :: 3
Classifier: License :: OSI Approved :: MIT License
Classifier: Operating System :: OS Independent
Requires-Python: >=3.6
